django_keyed_urls-0.4.1.dist-info/DESCRIPTION.rst
django_keyed_urls-0.4.1.dist-info/METADATA
django_keyed_urls-0.4.1.dist-info/RECORD
django_keyed_urls-0.4.1.dist-info/WHEEL
django_keyed_urls-0.4.1.dist-info/pydist.json
django_keyed_urls-0.4.1.dist-info/top_level.txt
keyed_urls/__init__.py
keyed_urls/admin.py
keyed_urls/models.py
keyed_urls/translation.py
keyed_urls/urls.py
keyed_urls/views.py
keyed_urls/locale/de/LC_MESSAGES/django.mo
keyed_urls/locale/de/LC_MESSAGES/django.po
keyed_urls/templatetags/__init__.py
keyed_urls/templatetags/keyed_urls.py
